pyvideoconverter/__init__.py
pyvideoconverter/_version.py
pyvideoconverter/cli.py
pyvideoconverter/parallel.py
pyvideoconverter/video.py
pyvideoconverter/bin/pyvideoc
pyvideoconverter-2022.3.3.post1.data/scripts/pyvideoc
pyvideoconverter-2022.3.3.post1.dist-info/LICENSE
pyvideoconverter-2022.3.3.post1.dist-info/METADATA
pyvideoconverter-2022.3.3.post1.dist-info/WHEEL
pyvideoconverter-2022.3.3.post1.dist-info/top_level.txt
pyvideoconverter-2022.3.3.post1.dist-info/RECORD
